<?xml version="1.0" encoding="UTF-8" standalone="yes"?>
<c:chartSpace xmlns:c="http://schemas.openxmlformats.org/drawingml/2006/chart" xmlns:a="http://schemas.openxmlformats.org/drawingml/2006/main" xmlns:r="http://schemas.openxmlformats.org/officeDocument/2006/relationships" xmlns:c16r2="http://schemas.microsoft.com/office/drawing/2015/06/chart"><c:date1904 val="0"/><c:lang val="en-US"/><c:roundedCorners val="0"/><mc:AlternateContent xmlns:mc="http://schemas.openxmlformats.org/markup-compatibility/2006"><mc:Choice Requires="c14" xmlns:c14="http://schemas.microsoft.com/office/drawing/2007/8/2/chart"><c14:style val="102"/></mc:Choice><mc:Fallback><c:style val="2"/></mc:Fallback></mc:AlternateContent><c:chart><c:autoTitleDeleted val="1"/><c:plotArea><c:layout><c:manualLayout><c:layoutTarget val="inner"/><c:xMode val="edge"/><c:yMode val="edge"/><c:x val="7.6368313665431078E-2"/><c:y val="6.8715296729974201E-2"/><c:w val="0.90189102490981066"/><c:h val="0.55826185380497872"/></c:manualLayout></c:layout><c:lineChart><c:grouping val="standard"/><c:varyColors val="0"/><c:ser><c:idx val="0"/><c:order val="0"/><c:tx><c:strRef><c:f>Sheet1!$B$1</c:f><c:strCache><c:ptCount val="1"/><c:pt idx="0"><c:v>Contract and Temp as a % of Total Jobs</c:v></c:pt></c:strCache></c:strRef></c:tx><c:spPr><a:ln w="28575" cap="rnd"><a:solidFill><a:srgbClr val="07325F"/></a:solidFill><a:prstDash val="solid"/><a:round/></a:ln><a:effectLst/></c:spPr><c:marker><c:symbol val="none"/></c:marker><c:dPt><c:idx val="10"/><c:marker><c:symbol val="none"/></c:marker><c:bubble3D val="0"/><c:extLst><c:ext uri="{C3380CC4-5D6E-409C-BE32-E72D297353CC}" xmlns:c16="http://schemas.microsoft.com/office/drawing/2014/chart"><c16:uniqueId val="{00000000-D396-4C63-941E-540C8E77E9DB}"/></c:ext></c:extLst></c:dPt><c:dPt><c:idx val="11"/><c:marker><c:symbol val="none"/></c:marker><c:bubble3D val="0"/><c:extLst><c:ext uri="{C3380CC4-5D6E-409C-BE32-E72D297353CC}" xmlns:c16="http://schemas.microsoft.com/office/drawing/2014/chart"><c16:uniqueId val="{00000001-D396-4C63-941E-540C8E77E9DB}"/></c:ext></c:extLst></c:dPt><c:dPt><c:idx val="12"/><c:marker><c:symbol val="none"/></c:marker><c:bubble3D val="0"/><c:extLst><c:ext uri="{C3380CC4-5D6E-409C-BE32-E72D297353CC}" xmlns:c16="http://schemas.microsoft.com/office/drawing/2014/chart"><c16:uniqueId val="{00000002-D396-4C63-941E-540C8E77E9DB}"/></c:ext></c:extLst></c:dPt><c:dPt><c:idx val="13"/><c:marker><c:symbol val="none"/></c:marker><c:bubble3D val="0"/><c:extLst><c:ext uri="{C3380CC4-5D6E-409C-BE32-E72D297353CC}" xmlns:c16="http://schemas.microsoft.com/office/drawing/2014/chart"><c16:uniqueId val="{00000003-D396-4C63-941E-540C8E77E9DB}"/></c:ext></c:extLst></c:dPt><c:dPt><c:idx val="21"/><c:marker><c:symbol val="none"/></c:marker><c:bubble3D val="0"/><c:extLst><c:ext uri="{C3380CC4-5D6E-409C-BE32-E72D297353CC}" xmlns:c16="http://schemas.microsoft.com/office/drawing/2014/chart"><c16:uniqueId val="{00000004-D396-4C63-941E-540C8E77E9DB}"/></c:ext></c:extLst></c:dPt><c:dPt><c:idx val="22"/><c:marker><c:symbol val="none"/></c:marker><c:bubble3D val="0"/><c:extLst><c:ext uri="{C3380CC4-5D6E-409C-BE32-E72D297353CC}" xmlns:c16="http://schemas.microsoft.com/office/drawing/2014/chart"><c16:uniqueId val="{00000005-D396-4C63-941E-540C8E77E9DB}"/></c:ext></c:extLst></c:dPt><c:dPt><c:idx val="23"/><c:marker><c:symbol val="none"/></c:marker><c:bubble3D val="0"/><c:extLst><c:ext uri="{C3380CC4-5D6E-409C-BE32-E72D297353CC}" xmlns:c16="http://schemas.microsoft.com/office/drawing/2014/chart"><c16:uniqueId val="{00000006-D396-4C63-941E-540C8E77E9DB}"/></c:ext></c:extLst></c:dPt><c:cat><c:numRef><c:f>Sheet1!$A$2:$A$15</c:f><c:numCache><c:formatCode>mmm\-yy</c:formatCode><c:ptCount val="14"/><c:pt idx="0"><c:v>42552</c:v></c:pt><c:pt idx="1"><c:v>42583</c:v></c:pt><c:pt idx="2"><c:v>42614</c:v></c:pt><c:pt idx="3"><c:v>42644</c:v></c:pt><c:pt idx="4"><c:v>42675</c:v></c:pt><c:pt idx="5"><c:v>42705</c:v></c:pt><c:pt idx="6"><c:v>42736</c:v></c:pt><c:pt idx="7"><c:v>42767</c:v></c:pt><c:pt idx="8"><c:v>42795</c:v></c:pt><c:pt idx="9"><c:v>42826</c:v></c:pt><c:pt idx="10"><c:v>42856</c:v></c:pt><c:pt idx="11"><c:v>42887</c:v></c:pt><c:pt idx="12"><c:v>42917</c:v></c:pt><c:pt idx="13"><c:v>42948</c:v></c:pt></c:numCache></c:numRef></c:cat><c:val><c:numRef><c:f>Sheet1!$B$2:$B$15</c:f><c:numCache><c:formatCode>0%</c:formatCode><c:ptCount val="14"/><c:pt idx="0"><c:v>9.9000000000000008E-3</c:v></c:pt><c:pt idx="1"><c:v>8.3000000000000001E-3</c:v></c:pt><c:pt idx="2"><c:v>2.35E-2</c:v></c:pt><c:pt idx="3"><c:v>1.8200000000000001E-2</c:v></c:pt><c:pt idx="4"><c:v>2.5399999999999999E-2</c:v></c:pt><c:pt idx="5"><c:v>1.0800000000000001E-2</c:v></c:pt><c:pt idx="6"><c:v>3.1099999999999999E-2</c:v></c:pt><c:pt idx="7" formatCode="\+0.0%"><c:v>3.6900000000000002E-2</c:v></c:pt><c:pt idx="8" formatCode="\+0.0%"><c:v>3.9300000000000002E-2</c:v></c:pt><c:pt idx="9" formatCode="\+0.0%"><c:v>3.7400000000000003E-2</c:v></c:pt><c:pt idx="10" formatCode="\+0.0%"><c:v>4.8899999999999999E-2</c:v></c:pt><c:pt idx="11" formatCode="\+0.0%"><c:v>4.6100000000000002E-2</c:v></c:pt><c:pt idx="12" formatCode="\+0.0%"><c:v>4.3700000000000003E-2</c:v></c:pt><c:pt idx="13" formatCode="\+0.0%"><c:v>4.3299999999999998E-2</c:v></c:pt></c:numCache></c:numRef></c:val><c:smooth val="0"/><c:extLst><c:ext uri="{C3380CC4-5D6E-409C-BE32-E72D297353CC}" xmlns:c16="http://schemas.microsoft.com/office/drawing/2014/chart"><c16:uniqueId val="{00000009-D396-4C63-941E-540C8E77E9DB}"/></c:ext></c:extLst></c:ser><c:dLbls><c:showLegendKey val="0"/><c:showVal val="0"/><c:showCatName val="0"/><c:showSerName val="0"/><c:showPercent val="0"/><c:showBubbleSize val="0"/></c:dLbls><c:smooth val="0"/><c:axId val="230570240"/><c:axId val="230572032"/></c:lineChart><c:dateAx><c:axId val="230570240"/><c:scaling><c:orientation val="minMax"/></c:scaling><c:delete val="0"/><c:axPos val="b"/><c:numFmt formatCode="mmm\-yy" sourceLinked="1"/><c:majorTickMark val="none"/><c:minorTickMark val="none"/><c:tickLblPos val="nextTo"/><c:spPr><a:noFill/><a:ln w="9525" cap="flat" cmpd="sng" algn="ctr"><a:solidFill><a:schemeClr val="tx1"/></a:solidFill><a:round/></a:ln><a:effectLst/></c:spPr><c:txPr><a:bodyPr rot="-2700000" spcFirstLastPara="1" vertOverflow="ellipsis" wrap="square" anchor="ctr" anchorCtr="1"/><a:lstStyle/><a:p><a:pPr algn="ctr"><a:defRPr lang="en-US" sz="800" b="0" i="0" u="none" strike="noStrike" kern="1200" baseline="0"><a:solidFill><a:schemeClr val="tx1"><a:lumMod val="65000"/><a:lumOff val="35000"/></a:schemeClr></a:solidFill><a:latin typeface="+mn-lt"/><a:ea typeface="+mn-ea"/><a:cs typeface="+mn-cs"/></a:defRPr></a:pPr><a:endParaRPr lang="en-US"/></a:p></c:txPr><c:crossAx val="230572032"/><c:crosses val="autoZero"/><c:auto val="1"/><c:lblOffset val="100"/><c:baseTimeUnit val="months"/></c:dateAx><c:valAx><c:axId val="230572032"/><c:scaling><c:orientation val="minMax"/><c:max val="5.000000000000001E-2"/><c:min val="0"/></c:scaling><c:delete val="0"/><c:axPos val="l"/><c:numFmt formatCode="0%" sourceLinked="0"/><c:majorTickMark val="none"/><c:minorTickMark val="none"/><c:tickLblPos val="nextTo"/><c:spPr><a:noFill/><a:ln><a:solidFill><a:schemeClr val="tx1"/></a:solidFill></a:ln><a:effectLst/></c:spPr><c:txPr><a:bodyPr rot="-60000000" spcFirstLastPara="1" vertOverflow="ellipsis" vert="horz" wrap="square" anchor="ctr" anchorCtr="1"/><a:lstStyle/><a:p><a:pPr><a:defRPr sz="800" b="0" i="0" u="none" strike="noStrike" kern="1200" baseline="0"><a:solidFill><a:schemeClr val="tx1"><a:lumMod val="65000"/><a:lumOff val="35000"/></a:schemeClr></a:solidFill><a:latin typeface="+mn-lt"/><a:ea typeface="+mn-ea"/><a:cs typeface="+mn-cs"/></a:defRPr></a:pPr><a:endParaRPr lang="en-US"/></a:p></c:txPr><c:crossAx val="230570240"/><c:crosses val="autoZero"/><c:crossBetween val="between"/><c:majorUnit val="1.0000000000000002E-2"/></c:valAx><c:spPr><a:noFill/><a:ln><a:noFill/></a:ln><a:effectLst/></c:spPr></c:plotArea><c:plotVisOnly val="1"/><c:dispBlanksAs val="gap"/><c:showDLblsOverMax val="0"/></c:chart><c:spPr><a:noFill/><a:ln><a:noFill/></a:ln><a:effectLst/></c:spPr><c:txPr><a:bodyPr/><a:lstStyle/><a:p><a:pPr><a:defRPr/></a:pPr><a:endParaRPr lang="en-US"/></a:p></c:txPr><c:externalData r:id="rId3"><c:autoUpdate val="0"/></c:externalData></c:chartSpace>