<?xml version="1.0" encoding="UTF-8" standalone="yes"?>
<Properties xmlns="http://schemas.openxmlformats.org/officeDocument/2006/extended-properties" xmlns:vt="http://schemas.openxmlformats.org/officeDocument/2006/docPropsVTypes"><Template>MP Template</Template><TotalTime>5007</TotalTime><Words>8918</Words><Application>Microsoft Office PowerPoint</Application><PresentationFormat>On-screen Show (4:3)</PresentationFormat><Paragraphs>1784</Paragraphs><Slides>58</Slides><Notes>1</Notes><HiddenSlides>0</HiddenSlides><MMClips>0</MMClips><ScaleCrop>false</ScaleCrop><HeadingPairs><vt:vector size="4" baseType="variant"><vt:variant><vt:lpstr>Theme</vt:lpstr></vt:variant><vt:variant><vt:i4>1</vt:i4></vt:variant><vt:variant><vt:lpstr>Slide Titles</vt:lpstr></vt:variant><vt:variant><vt:i4>58</vt:i4></vt:variant></vt:vector></HeadingPairs><TitlesOfParts><vt:vector size="59" baseType="lpstr"><vt:lpstr>MP Template</vt:lpstr><vt:lpstr>Management Presentation</vt:lpstr><vt:lpstr>Introductions</vt:lpstr><vt:lpstr>Compelling Channel Presence within the Imaging Industry</vt:lpstr><vt:lpstr>Table of Contents</vt:lpstr><vt:lpstr>Compelling Investment Opportunity</vt:lpstr><vt:lpstr>Unique Market Leading Platform</vt:lpstr><vt:lpstr>Differentiated Size and Scale</vt:lpstr><vt:lpstr>Enhanced Business Model… </vt:lpstr><vt:lpstr>…is Driving a Significant Increase in Profitability… </vt:lpstr><vt:lpstr>…and Positions Katun for Growth</vt:lpstr><vt:lpstr>Compelling Value Proposition </vt:lpstr><vt:lpstr>Compelling Value Proposition (continued)</vt:lpstr><vt:lpstr>Summary Investment Thesis</vt:lpstr><vt:lpstr>Product Portfolio and Industry Leading Brands </vt:lpstr><vt:lpstr>Product Categories – Imaging Supplies</vt:lpstr><vt:lpstr>Product Categories – Parts</vt:lpstr><vt:lpstr>Product Categories – Photoreceptors and Drum Unit Cartridges</vt:lpstr><vt:lpstr>Product Categories – Accessories and Other Products</vt:lpstr><vt:lpstr>Industry Leading Brands</vt:lpstr><vt:lpstr>Superior Operations</vt:lpstr><vt:lpstr>Leading Product Development and Sourcing Capabilities</vt:lpstr><vt:lpstr>Leading Product Development and Sourcing Capabilities (continued)</vt:lpstr><vt:lpstr>First-to-Market New Product Development Agility and Expertise</vt:lpstr><vt:lpstr>Patent Clearance Process &amp; Worldwide Strategy</vt:lpstr><vt:lpstr>Proactive Effective Lifecycle Management</vt:lpstr><vt:lpstr>Innovative Approach to Inventory Management</vt:lpstr><vt:lpstr>Innovative Approach to Inventory Management (continued)</vt:lpstr><vt:lpstr>Supplier Partnerships</vt:lpstr><vt:lpstr>Global Scale and Footprint</vt:lpstr><vt:lpstr>Facilities Overview</vt:lpstr><vt:lpstr>Research and Development Center</vt:lpstr><vt:lpstr>Sales, Marketing &amp; Customers</vt:lpstr><vt:lpstr>Compelling Channel Presence within the Imaging Industry</vt:lpstr><vt:lpstr>Sales Overview</vt:lpstr><vt:lpstr>Marketing Overview</vt:lpstr><vt:lpstr>Long-Term, Entrenched Customer Relationships</vt:lpstr><vt:lpstr>Expanding Share of Wallet and Targeting Capabilities</vt:lpstr><vt:lpstr>Case Study: Targeting Customers for Additional Revenue</vt:lpstr><vt:lpstr>Katun Dealer Fleet Management (“KDFM”)</vt:lpstr><vt:lpstr>Growth Opportunities</vt:lpstr><vt:lpstr>Market Overview</vt:lpstr><vt:lpstr>Clear Path for Continued Growth and Accelerating Profitability</vt:lpstr><vt:lpstr>Increase Share in the Color MFD Market</vt:lpstr><vt:lpstr>Increase Share in the Color MFD Market (continued)</vt:lpstr><vt:lpstr>Increase Penetration of the Printer-Based Toner Market</vt:lpstr><vt:lpstr>Introduce a Refurbished Imaging Equipment Offering</vt:lpstr><vt:lpstr>Enhance Service Level Value Proposition</vt:lpstr><vt:lpstr>Financial Review</vt:lpstr><vt:lpstr>Financial Summary </vt:lpstr><vt:lpstr>Summary of Historical Revenue Drivers</vt:lpstr><vt:lpstr>Strong Performance through Q1 2017 </vt:lpstr><vt:lpstr>Bridge to 2017F Budget - Revenue</vt:lpstr><vt:lpstr>Bridge to 2017F Budget - EBITDA</vt:lpstr><vt:lpstr>Adjustments</vt:lpstr><vt:lpstr>Capital Expenditures and Free Cash Flow</vt:lpstr><vt:lpstr>Conclusion</vt:lpstr><vt:lpstr>Summary Investment Thesis</vt:lpstr><vt:lpstr>Final Comments</vt:lpstr></vt:vector></TitlesOfParts><LinksUpToDate>false</LinksUpToDate><SharedDoc>false</SharedDoc><HyperlinksChanged>false</HyperlinksChanged><AppVersion>14.0000</AppVersion></Properties>